erajs/__init__.py
erajs/api.py
erajs/engine.py
erajs/mid.py
erajs/docs/插件简介与系统介绍.md
erajs/docs/插件结构与原理.md
erajs/docs/数据结构.json
erajs/docs/数据结构.md
erajs/docs/生命周期.md
erajs/plugin/EraAI.py
erajs/plugin/EraAchievement.py
erajs/plugin/EraAct.py
erajs/plugin/EraAvantar.py
erajs/plugin/EraBattle.py
erajs/plugin/EraCareer.py
erajs/plugin/EraChaos.py
erajs/plugin/EraConsole.py
erajs/plugin/EraData.py
erajs/plugin/EraDebug.py
erajs/plugin/EraDynamic.py
erajs/plugin/EraERB.py
erajs/plugin/EraEmotion.py
erajs/plugin/EraEstate.py
erajs/plugin/EraEvent.py
erajs/plugin/EraFestival.py
erajs/plugin/EraGuanXi.py
erajs/plugin/EraHistory.py
erajs/plugin/EraIndoor.py
erajs/plugin/EraItem.py
erajs/plugin/EraKojo.py
erajs/plugin/EraKojoGen.py
erajs/plugin/EraLuck.py
erajs/plugin/EraMap.py
erajs/plugin/EraMarket.py
erajs/plugin/EraNative.py
erajs/plugin/EraNet.py
erajs/plugin/EraRealtime.py
erajs/plugin/EraSElement.py
erajs/plugin/EraTern.py
erajs/plugin/EraTextTemp.py
erajs/plugin/EraTime.py
erajs/plugin/EraUI.py
erajs-0.1.0.181116.3.dist-info/LICENSE
erajs-0.1.0.181116.3.dist-info/METADATA
erajs-0.1.0.181116.3.dist-info/WHEEL
erajs-0.1.0.181116.3.dist-info/top_level.txt
erajs-0.1.0.181116.3.dist-info/RECORD
